rufus/__init__.py
rufus/client.py
rufus/config.py
rufus/content_filter.py
rufus/utils.py
rufus_crawler-0.1.1.dist-info/LICENSE
rufus_crawler-0.1.1.dist-info/METADATA
rufus_crawler-0.1.1.dist-info/WHEEL
rufus_crawler-0.1.1.dist-info/entry_points.txt
rufus_crawler-0.1.1.dist-info/top_level.txt
rufus_crawler-0.1.1.dist-info/RECORD
