Metadata-Version: 2.1
Name: rufus_crawler
Version: 0.1.1
Summary: A web crawler and content filtering tool using OpenAI.
Home-page: https://github.com/amanattar/rufus_crawler
Author: Amanul Rahiman Attar
Author-email: attar.aman29@gmail.com
License: MIT
Classifier: Programming Language :: Python :: 3
Classifier: License :: OSI Approved :: MIT License
Classifier: Operating System :: OS Independent
Requires-Python: >=3.10
License-File: LICENSE
Requires-Dist: beautifulsoup4
Requires-Dist: requests
Requires-Dist: openai
Requires-Dist: selenium
Requires-Dist: webdriver-manager
Requires-Dist: PyYAML
